XWindows/__init__.py
XWindows/keys.py
XWindows/windows.py
XWindows-0.0.7.dist-info/LICENSE.txt
XWindows-0.0.7.dist-info/METADATA
XWindows-0.0.7.dist-info/WHEEL
XWindows-0.0.7.dist-info/top_level.txt
XWindows-0.0.7.dist-info/RECORD
