Metadata-Version: 2.1
Name: XWindows
Version: 0.0.7
Summary: X Server client to access windows and automate keypresses
Home-page: UNKNOWN
Author: sleepingsaint
Author-email: suryasantosh14523@gmail.com
License: MIT License
Project-URL: GitHub Project, https://github.com/sleepingsaint/XWindows
Project-URL: Issue Tracker, https://github.com/sleepingsaint/XWindows/issues
Keywords: python3,XServer,Xlib,linux
Platform: UNKNOWN
Classifier: Development Status :: 5 - Production/Stable
Classifier: Intended Audience :: Education
Classifier: Programming Language :: Python :: 3
Classifier: Operating System :: POSIX :: Linux
Classifier: Environment :: X11 Applications
Classifier: Intended Audience :: Developers
Classifier: License :: OSI Approved :: MIT License
Requires-Dist: python-xlib
